exabyte/__init__.py
exabyte/main.py
exabyte-0.0.8.dist-info/METADATA
exabyte-0.0.8.dist-info/WHEEL
exabyte-0.0.8.dist-info/top_level.txt
exabyte-0.0.8.dist-info/RECORD
